hitfactorpy_sqlalchemy/__init__.py
hitfactorpy_sqlalchemy/__main__.py
hitfactorpy_sqlalchemy/alembic.ini
hitfactorpy_sqlalchemy/alembic_utils.py
hitfactorpy_sqlalchemy/cli/__init__.py
hitfactorpy_sqlalchemy/cli/import_.py
hitfactorpy_sqlalchemy/cli/migrate.py
hitfactorpy_sqlalchemy/cli/model/__init__.py
hitfactorpy_sqlalchemy/cli/model/match_report.py
hitfactorpy_sqlalchemy/defaults.py
hitfactorpy_sqlalchemy/env.py
hitfactorpy_sqlalchemy/migrations/README
hitfactorpy_sqlalchemy/migrations/env.py
hitfactorpy_sqlalchemy/migrations/script.py.mako
hitfactorpy_sqlalchemy/migrations/versions/643ac9d51943_add_matchreport_region_column.py
hitfactorpy_sqlalchemy/migrations/versions/77fff15ec613_add_more_fields_to_matchreport.py
hitfactorpy_sqlalchemy/migrations/versions/ffb9404a7bbf_init.py
hitfactorpy_sqlalchemy/orm/__init__.py
hitfactorpy_sqlalchemy/orm/expression.py
hitfactorpy_sqlalchemy/orm/models.py
hitfactorpy_sqlalchemy/py.typed
hitfactorpy_sqlalchemy/session.py
hitfactorpy_sqlalchemy-0.1.0.dist-info/METADATA
hitfactorpy_sqlalchemy-0.1.0.dist-info/WHEEL
hitfactorpy_sqlalchemy-0.1.0.dist-info/entry_points.txt
hitfactorpy_sqlalchemy-0.1.0.dist-info/RECORD
