Metadata-Version: 2.1
Name: hitfactorpy-sqlalchemy
Version: 0.1.0
Summary: Import and manage practical match reports with SQLAlchemy
Home-page: https://cahna.github.io/hitfactorpy-sqlalchemy/
Keywords: uspsa,orm
Author: Conor Heine
Author-email: conor.heine@gmail.com
Requires-Python: >=3.10,<3.12
Classifier: Development Status :: 3 - Alpha
Classifier: Intended Audience :: Developers
Classifier: Intended Audience :: System Administrators
Classifier: Operating System :: OS Independent
Classifier: Programming Language :: Python
Classifier: Programming Language :: Python :: 3
Classifier: Programming Language :: Python :: 3.10
Classifier: Programming Language :: Python :: 3.11
Classifier: Programming Language :: Python :: 3
Classifier: Programming Language :: Python :: 3 :: Only
Classifier: Programming Language :: Python :: 3.10
Classifier: Programming Language :: Python :: 3.11
Classifier: Topic :: Database
Classifier: Topic :: Other/Nonlisted Topic
Classifier: Topic :: Scientific/Engineering :: Information Analysis
Classifier: Topic :: Scientific/Engineering :: Interface Engine/Protocol Translator
Classifier: Topic :: Software Development :: Code Generators
Classifier: Topic :: Software Development :: Libraries :: Python Modules
Classifier: Topic :: Software Development :: Object Brokering
Classifier: Typing :: Typed
Requires-Dist: alembic (>=1.9.2,<2.0.0)
Requires-Dist: asyncpg (>=0.27.0,<0.28.0)
Requires-Dist: hitfactorpy (>=1.0.0,<2.0.0)
Requires-Dist: inflection (>=0.5.1,<0.6.0)
Requires-Dist: psycopg2-binary (>=2.9.5,<3.0.0)
Requires-Dist: rich (<13)
Requires-Dist: sqlalchemy-continuum (>=1.3.14,<2.0.0)
Requires-Dist: sqlalchemy-utils (>=0.39.0,<0.40.0)
Requires-Dist: sqlalchemy[asyncio,mypy] (>=1.4,<2.0)
Requires-Dist: typer[all] (>=0.7.0,<0.8.0)
Project-URL: Bug Tracker, https://github.com/cahna/hitfactorpy-sqlalchemy/issues
Project-URL: Documentation, https://cahna.github.io/hitfactorpy-sqlalchemy/
Project-URL: Repository, https://github.com/cahna/hitfactorpy-sqlalchemy
